src/__init__.py
src/agent.py
sweep_sdk-0.0.0.dist-info/METADATA
sweep_sdk-0.0.0.dist-info/WHEEL
sweep_sdk-0.0.0.dist-info/RECORD
